naapi/__init__.py
naapi/aioapi.py
naapi/api.py
naapi-0.1.7.dist-info/METADATA
naapi-0.1.7.dist-info/WHEEL
naapi-0.1.7.dist-info/top_level.txt
naapi-0.1.7.dist-info/RECORD
