Metadata-Version: 2.1
Name: naapi
Version: 0.1.7
Summary: NetActuate API SDK, With both normal and asyncio packages
Home-page: https://github.com/netactuate/naapi/
Author: NetActuate
Author-email: support@netactuate.com
License: MIT
Keywords: api sdk cloud python netactuate
Platform: UNKNOWN
Classifier: Environment :: Web Environment
Classifier: Intended Audience :: Developers
Classifier: License :: OSI Approved :: MIT License
Classifier: Programming Language :: Python
Classifier: Programming Language :: Python :: 2.7
Classifier: Programming Language :: Python :: 3.7
Classifier: Topic :: Internet :: WWW/HTTP
Classifier: Topic :: Software Development :: Libraries
Classifier: Topic :: Software Development :: Libraries :: Python Modules
Requires-Dist: requests (>=2.21.0)
